ucdp_sv-0.25.0.dist-info/METADATA
ucdp_sv-0.25.0.dist-info/WHEEL
ucdp_sv-0.25.0.dist-info/entry_points.txt
ucdp_sv-0.25.0.dist-info/licenses/LICENSE
ucdpsv/__init__.py
ucdpsv/svexprresolver.py
ucdpsv/svimporter.py
ucdpsv/ucdp-templates/sv.mako
ucdp_sv-0.25.0.dist-info/RECORD
