Metadata-Version: 2.1
Name: ucdp-sv
Version: 0.25.0
Summary: Unified Chip Design Platform - System Verilog Support
Classifier: Programming Language :: Python :: 3
Classifier: Operating System :: OS Independent
Project-URL: Homepage, https://github.com/nbiotcloud/ucdp-sv
Project-URL: Documentation, https://ucdp-sv.readthedocs.io/en/stable/
Project-URL: Bug Tracker, https://github.com/nbiotcloud/ucdp-sv/issues
Requires-Python: <4.0,>=3.10.0
Requires-Dist: aligntext>=1.0.0
Requires-Dist: ucdp>=0.41.0
Requires-Dist: makolator>=2.9.1
Requires-Dist: ucdp-glbl>=1.4.0
Requires-Dist: hdl-parser>=0.6.1
